{
  "site_name": "LCPD",
  "backend_url": "https://admin.lcpd-abuja.com",
  "number_one": "07066920710",
  "number_two": "09048088823",
  "global_email": "info@lcpd-abuja.com",
  "address": "Plot 678 Axis Plaza Opp MRS/NNPC filling station by Gudu",
  "facebook": "https://web.facebook.com/lcpdtech",
  "instagram": "https://www.instagram.com/lcpdtech/",
  "twitter": "https://x.com/lcpdtechabuja",
  "whatsapp": "https://wa.me/2347066920710",
  "tictok": "https://www.tiktok.com/@lcpd.tech.abuja?is_from_webapp=1&sender_device=pc",
  "youtube": "https://www.youtube.com/@LCPDTECH"
}